<?xml version="1.0"?>
<!DOCTYPE layout-templates PUBLIC "-//Liferay//DTD Layout Templates 6.1.0//EN" "http://www.liferay.com/dtd/liferay-layout-templates_6_1_0.dtd">

<layout-templates>
	<custom>
		<layout-template id="2col_4_8_Foundation" name="2col 4 8 Foundation">
			<template-path>/2col_4_8_Foundation.tpl</template-path>
			<wap-template-path>/2col_4_8_Foundation.wap.tpl</wap-template-path>
			<thumbnail-path>/2col_4_8_Foundation.png</thumbnail-path>
		</layout-template>
	</custom>
</layout-templates>